Metadata-Version: 2.1
Name: lyricsScraper
Version: 1.0.4
Summary: You can get lyrics from genius with many usefull functions.
Home-page: https://github.com/letsplaywithstrings/lyrcisScraper
Author: Ahmet Metin
Author-email: ahmet.metin817@gmail.com
License: UNKNOWN
Download-URL: https://github.com/letsplaywithstrings/lyrcisScraper/archive/1.0.4.tar.gz
Keywords: Lyrics,Artist
Platform: UNKNOWN
Classifier: Development Status :: 4 - Beta
Classifier: Intended Audience :: Developers
Classifier: Topic :: Software Development :: Build Tools
Classifier: License :: OSI Approved :: MIT License
Classifier: Programming Language :: Python :: 3.6
Classifier: Programming Language :: Python :: 3.7
Classifier: Programming Language :: Python :: 3.8
Classifier: Programming Language :: Python :: 3.9
